LICENSE
MANIFEST.in
README.md
setup.cfg
setup.py
./mmseg/ops/csrc/lib_mpl.cpp
./mmseg/ops/csrc/pybind.cpp
mmseg/__init__.py
mmseg/version.py
mmseg/apis/__init__.py
mmseg/apis/export.py
mmseg/apis/fake_input.py
mmseg/apis/inference.py
mmseg/apis/test.py
mmseg/apis/train.py
mmseg/core/__init__.py
mmseg/core/evaluation/__init__.py
mmseg/core/evaluation/class_names.py
mmseg/core/evaluation/eval_hooks.py
mmseg/core/evaluation/metrics.py
mmseg/core/hooks/__init__.py
mmseg/core/hooks/auxiliary_hooks.py
mmseg/core/hooks/ema.py
mmseg/core/hooks/optimizer.py
mmseg/core/lr/__init__.py
mmseg/core/lr/base_lr_hook.py
mmseg/core/lr/customcos_lr_hook.py
mmseg/core/lr/customstep_lr_hook.py
mmseg/core/ops/__init__.py
mmseg/core/ops/conv.py
mmseg/core/ops/losses.py
mmseg/core/ops/math.py
mmseg/core/ops/norm.py
mmseg/core/seg/__init__.py
mmseg/core/seg/builder.py
mmseg/core/seg/sampler/__init__.py
mmseg/core/seg/sampler/base_pixel_sampler.py
mmseg/core/seg/sampler/class_weighting_pixel_sampler.py
mmseg/core/seg/sampler/max_pooling_pixel_sampler.py
mmseg/core/seg/sampler/ohem_pixel_sampler.py
mmseg/core/utils/__init__.py
mmseg/core/utils/checkpoint.py
mmseg/core/utils/config.py
mmseg/core/utils/misc.py
mmseg/datasets/__init__.py
mmseg/datasets/ade.py
mmseg/datasets/builder.py
mmseg/datasets/chase_db1.py
mmseg/datasets/cityscapes.py
mmseg/datasets/coco_stuff.py
mmseg/datasets/custom.py
mmseg/datasets/dataset_wrappers.py
mmseg/datasets/drive.py
mmseg/datasets/hrf.py
mmseg/datasets/kvasir.py
mmseg/datasets/pascal_context.py
mmseg/datasets/stare.py
mmseg/datasets/voc.py
mmseg/datasets/pipelines/__init__.py
mmseg/datasets/pipelines/compose.py
mmseg/datasets/pipelines/formating.py
mmseg/datasets/pipelines/loading.py
mmseg/datasets/pipelines/test_time_aug.py
mmseg/datasets/pipelines/transforms.py
mmseg/integration/__init__.py
mmseg/integration/nncf/__init__.py
mmseg/integration/nncf/compression.py
mmseg/integration/nncf/compression_hooks.py
mmseg/integration/nncf/config.py
otxseg.egg-info/PKG-INFO
otxseg.egg-info/SOURCES.txt
otxseg.egg-info/dependency_links.txt
otxseg.egg-info/not-zip-safe
otxseg.egg-info/requires.txt
otxseg.egg-info/top_level.txt
