Metadata-Version: 2.1
Name: otxseg
Version: 0.3.0
Summary: Temporary OTX fork of MMSegmenation Semantic Segmentation Toolbox and Benchmark
Home-page: http://github.com/openvinotoolkit/mmsegmentation
Author: OpenMMLab, Intel
Author-email: songki.choi@intel.com
License: Apache License 2.0
Keywords: computer vision,semantic segmentation
Classifier: Development Status :: 4 - Beta
Classifier: License :: OSI Approved :: Apache Software License
Classifier: Operating System :: OS Independent
Classifier: Programming Language :: Python :: 3.6
Classifier: Programming Language :: Python :: 3.7
Classifier: Programming Language :: Python :: 3.8
Provides-Extra: all
Provides-Extra: tests
Provides-Extra: build
Provides-Extra: optional
License-File: LICENSE
